{"@class":"Animation","AnimationType":"Invalid","id":{"uuid":"F4447447-74CC-4EC2-80E9-651933A4870F"},"is_imported":false,"tracks":[{"@class":"Vector3BehaviorTrack","accessor":"ColorBlendAccessor","clips":[{"@class":"Vector3BehaviorClip","beginTime":0,"behavior":{"@class":"Vector3BezierBehavior","frames":[{"@class":"Vector3BezierKeyFrame","formula":{"@class":"Vector3ExpressionFormula","expression":"var v[3]:={0.827451,0.176471,0.176471};return[v];"},"order":"constant","point1":{"values":[1.0,0.0]},"point2":{"values":[1.0,0.0]},"time":0,"transition":true},{"@class":"Vector3BezierKeyFrame","formula":{"@class":"Vector3ExpressionFormula","expression":"var v[3]:={1,1,1};return[v];"},"order":"constant","point1":{"values":[1.0,0.0]},"point2":{"values":[1.0,0.0]},"time":500,"transition":true},{"@class":"Vector3BezierKeyFrame","formula":{"@class":"Vector3ExpressionFormula","expression":"var v[3]:={0.827451,0.176471,0.176471};return[v];"},"order":"cubic","point1":{"values":[0.6000000238418579,0.03999999910593033]},"point2":{"values":[0.9800000190734863,0.35499998927116394]},"time":200,"transition":true}]},"duration":500,"script":"Vector3ValueBehaviorClipScript"}],"script":"Vector3BehaviorTrackScript"}]}