{"@class":"PhysicsBody","bounciness":0.5,"ccdMotionThreshold":0.05000000074505806,"ccdSweptSphereRadius":1.0,"friction":1.0,"gravity":{"values":[0.0,0.0,0.0]},"id":{"uuid":"3918B8A0-EEC2-46C2-84A7-A8F98B5D2F3F"},"initAngularVelocity":{"values":[0.0,0.0,0.0]},"initLinearVelocity":{"values":[0.0,0.0,0.0]},"lockPositionX":false,"lockPositionY":false,"lockPositionZ":false,"lockRotationX":false,"lockRotationY":false,"lockRotationZ":false,"mass":10.0,"physBodyType":"static","physSurfaceType":"defaultSurfaceType","useCCD":false,"useCustomGravity":false,"useLocalInitialVelocities":false}