{"@class":"Script_SkyBox","DefaultTextureEnv":{"uuid":"DBA0832C-1C08-4EDF-B68D-78924A6440F3"},"DefaultTextureIrrEnv":{"uuid":"A43B9163-2F11-4E33-A263-B5DFDCBCAA42"},"DefaultTextureSkyBox":{"uuid":"E50211F2-467D-4014-8EA1-179880DDF3CE"},"blendFactor":0.0,"btmColor":{"values":[13.0,26.0,64.0]},"enableOnAwake":true,"id":{"uuid":"8BC74022-8583-422A-9F4E-C2DDD5EFCD8C"},"mdlColor":{"values":[219.23345947265625,230.7509765625,242.42800903320313]},"name":"Script_SkyBox","resolution":256,"scattering":0.75,"topColor":{"values":[64.0,127.0,191.0]}}